my_own_package/__init__.py
Laura_project_hello-0.1.0.dist-info/METADATA
Laura_project_hello-0.1.0.dist-info/WHEEL
Laura_project_hello-0.1.0.dist-info/top_level.txt
Laura_project_hello-0.1.0.dist-info/RECORD
