Metadata-Version: 2.1
Name: Laura-project-hello
Version: 0.1.0
Summary: says hello to owner
Home-page: UNKNOWN
Author: Laura R.
Author-email: ritzylaura4@gmail.com
License: UNKNOWN
Platform: UNKNOWN
